korean_regex-0.2.0.dist-info/METADATA
korean_regex-0.2.0.dist-info/WHEEL
korean_regex-0.2.0.dist-info/license_files/LICENSE
kre/_regex.py
kre/__init__.py
kre/_core.pyi
kre/_core.cpython-39-i386-linux-gnu.so
korean_regex-0.2.0.dist-info/RECORD
