Metadata-Version: 2.3
Name: korean-regex
Version: 0.2.0
Classifier: Programming Language :: Rust
Classifier: Programming Language :: Python :: Implementation :: CPython
Classifier: Programming Language :: Python :: Implementation :: PyPy
Classifier: Intended Audience :: Developers
Classifier: License :: OSI Approved :: MIT License
Classifier: Programming Language :: Python
Classifier: Programming Language :: Python :: 3
Classifier: Natural Language :: Korean
Classifier: Typing :: Typed
License-File: LICENSE
Summary: Regex for Korean
Keywords: regex,korean
Author-email: ilotoki0804 <ilotoki0804@gmail.com>
Requires-Python: >=3.8
Project-URL: Source, https://github.com/ilotoki0804/korean-regex
Project-URL: Tracker, https://github.com/ilotoki0804/korean-regex/issues
Project-URL: Funding, https://toss.me/ilotoki
